<tazs>
<taz id="51" edges="218948502 -218948502 458450992 -458450992 403521404 -403521404 458438675 -458438675 458438683 -458438683 19937715#0 19937715#1 19937715#2 19937715#3 480220937 19937716#0 19937716#1 19937716#2 36675279#0 -36675279#0 126012206 -126012206 126012207#1 -126012207#1"/>
<taz id="22" edges="123213513 -123213513 329384201#0 329384201#1 -329384201#0 -329384201#1 329384203 -329384203 465416567#0 465416567#2 -465416567#0 -465416567#2 329384211 465416571 465416572 465416575#1 465416577#0 132093451 329384202 219132791#0 -219132791#0 465413240#1 -465413240#1 465413238 -465413238 465413243#1 -465413243#1 21343730"/>
<taz id="50" edges="26134691 329989912 60116252#0 60116252#1 36675282 329989228 -329989228 482327908#0 -482327908#0 329065110 329065118 329692109 329989914 -329989914 454827462 -454827462 4320453 329795964#1 -329795964#1 453989316 -453989316 465380603 -465380603 465380604 -465380604 215446976#2 464892586 464892587 132220912 -132220912 453989321 -453989321 457924062 -457924062 36675277 -36675277 215446977#1 -215446977#1 453989327 -453989327"/>
<taz id="49" edges="465381269 -465381269 115794578#1"/>
<taz id="42" edges="458246628 -458246628 41551804"/>
<taz id="24" edges="-455083978#0 -455083974#0 -24221231#1 -466675150 112863359#1 112863359#2"/>
<taz id="25" edges="329384204"/>
<taz id="27" edges="455083974#0 19891896#0 19891896#1 19891896#2 19891896#3 356391519 19896824#0 19896824#1"/>
<taz id="20" edges="104476238 479129085 456316923 361607072 -361607072 21258129 118773309 -118773309 361607071 19896202 435429811 80209250 370125650#1 370125650#2 370125650#3 370125650#4 60116382#0 60116382#1 60116382#2 422539631 -422539631 19894612"/>
<taz id="48" edges="4320463 374954611#0 374954611#1 329795985#0 329795985#1 374956192#0 374956192#1 374956192#2 -394908447#0 -394908447#1 -394908447#2 -394908447#3 394908447#2 394908447#3 394908447#0 394908447#1 -453999955#0 -394908447#5 -394908447#4 394908447#5 394908447#4 453999955#0 -454245380 454245380 -453999956#0 453999956#0 19937691 -19937691 181866866 -181866866 458446466#0 458446466#1 -458446466#0 -458446466#1 344948096 20319597#0 20319597#1 -20319597#0 -20319597#1 124134666#0 124134666#1 -124134666#0 -124134666#1 454844394 -454844394 95218183#1 95218183#0 -95218183#0 344947790 -344947790 374956190 -374956190 374956193#0 374956193#2 60116376#2 329796314#0 329796314#1 329796314#2 374956189#0 374956189#1 464894857 -464894857 464894862 -464894862 464896844 -464896844 20318499 454001075#0 454001075#1 15834351"/>
<taz id="23" edges="329384212 329384214#0 329384214#1 453963142 453981161#0 455083978#0 -300627772#1 165325606#1 329384215 19891899 108603837 -108603837 19894751#3 19894751#4 19894751#0 19894751#2 -19894751#0 -19894751#2 300414148#1 329384216"/>
<taz id="46" edges="41551810#0 41551810#1 41551810#2 19908068#0 19908068#1 141607352#0 141607352#1 141607352#2"/>
<taz id="47" edges="41551739 4883068#2 4883068#3 4883068#4 13503101#0 13503101#1 48921997#0 48921997#1 48921997#2 48921997#3 48921997#4 48921997#5 48921997#6"/>
<taz id="44" edges="454238784 -454238784 454238787#0 -454238787#0 454245382#1 -454245382#1 39368244 39368241#1 39368241#2 39368241#3 454238788 19908076#0 19908076#1 19908076#2 19908076#3 19908076#4 39368243"/>
<taz id="45" edges="19908071#2 19908071#0 19908071#3 -19908071#0 -19908071#3 19908073#2 19908073#3 19908073#4 60116252#2 60116252#4 60116252#5 60116252#6 19908075#2 19908075#3 19908075#0 19908075#1 -19908075#0 -19908075#1 41551807#0 41551807#1 -41551807#0 -41551807#1 465381271 -465381271 26442468#0 26442468#2"/>
<taz id="28" edges="-4687530#0 -456314147#0 -456314146 165325223#0 165325223#1 36597164 -36597164 41258633#0 41258633#1 41258633#2 41258633#3 205657782#0 205657782#1 205657782#2 205657782#3 205657782#4 36597165 165325226#0 165325226#1"/>
<taz id="29" edges="465416568 465416569 19896822#0 19896822#1 19896822#2 356391518 356391520"/>
<taz id="40" edges="454215277#0 454215275 454238785 45560662 45560675 45560670#0 45560670#1 45560670#2 80209244#0 80209244#1 320900389#0 320900389#1 320900389#2 320900389#3 320900389#4 475251116 126011883"/>
<taz id="41" edges="60116380#3 4320485#1 464935941#1 -464935941#1 60116376#0 60116376#1 60116381 396642608#1"/>
<taz id="1" edges="165265052#0 -165265052#0 465416564#0 -465416564#0 385879098#0"/>
<taz id="3" edges="165264484 165265055#0 165265055#1 165265055#2 165265055#3 133806981#0 133806981#1 -133806981#0 -133806981#1 133806981#2 -133806981#2 25367028#0 25367028#1 -25367028#0 -25367028#1 111771067 -111771067 111771071#0 111771071#1 -111771071#0 -111771071#1 329988460#0 329988460#1 -329988460#0 -329988460#1 19899281 -19899281 103974914#1 103974914#3 103974914#4 103974914#5 162975557 19899376 25367086 38700726#2 38700726#5 38700726#6 38700726#7 38700726#8 38700726#10 38700726#11 38700726#12 -38700726#2 -38700726#5 -38700726#6 -38700726#7 -38700726#8 -38700726#10 -38700726#11 -38700726#12 165217829 -165217829 20112467 -20112467 200638843#1 329988459#0 329988459#1 329988459#2 329988459#3 19899374#0 19899374#1 25367021#0 25367021#1 -25367021#0 -25367021#1"/>
<taz id="2" edges="20112623#0 20112623#1 -20112623#0 -20112623#1 464709529 -464709529 455713130 -455713130 455722367 -455722367 455722372 -455722372 20112792#0 20112792#1 20112792#2 20112792#3 -20112792#0 -20112792#1 -20112792#2 -20112792#3 25367322 129587034 455715711 -455715711 20112463#0 20112463#1 20112463#2 492899792 -492899792 20112793 20112458#0 20112458#1 20112458#2 20112458#3 20112458#4 20112458#5 20112458#7 20112458#8 25367228 20112457 -20112457 129587031 -129587031 41651789 -41651789 492899793#0 492899793#1 -492899793#0 -492899793#1 366840862#0 366840862#1 366840862#2 366840862#3 366840862#5 366840862#6 366840862#7 366840861"/>
<taz id="5" edges="19899867 35165792 35165799 19652361#2 15834714 19899276 41258971#1 -330153472#1 455083970#1 455083980#1 -455083980#1 465651305#1 25367003 103935602 -103935602 134811810#1 -134811810#1 41258976#1 -41258976#1 465656094#1 -465656094#1 103896396#1 103896396#2 103896396#3 8140256#2 39442470#0 118119100 118116148"/>
<taz id="4" edges="15834714 25366945 -25366945 455084002 463676555#0 463676555#1 463676555#2 463676555#3 463676555#4 463676555#7 19899784 118119100 454867946"/>
<taz id="7" edges="-465651305#1 330153472#1 -455083970#1 -41258971#1 4687641#0 4687641#3 165337364#1 165337364#4 165337364#7 461254932#1 -461254932#1 475694576#1 -475694576#1 455083994#1 -455083994#1 4320471#0 4320471#3 4320471#6 329694554#5 329694554#8 329694554#11 329694554#14 329694554#17 461254933#1 461254933#2"/>
<taz id="6" edges="-455084002 456874507 -456874507 456874546#1 -456874546#1 164976438#0 164976438#1 165325605 -165325605 313639754 313639760#0 -308658929#0 -36672937#1 36672937#1 37722302#1 -37722302#1 354710422 -354710422 450956616 -450956616 133806980#0 133806980#1 354710423 -354710423 25366817 -25366817 19899780 19899781 19899782 313639762"/>
<taz id="9" edges="48680979 329384217#1 329384217#4 329384217#7 330153470#1 465416576#1 399708740 48680975#1 -48680975#1 165217827#0 165217827#1 -165217827#0 -165217827#1 19912054 465411710#0 -465411710#0 465408858#1 -465408858#1 465408860#1 -465408860#1 465411709 -465411709 465411713#0 -465411713#0 465411715#1 -465411715#1 80278547#0"/>
<taz id="8" edges="-465649965#0 -455083975#0 -465649964#0 465649967#0 38956598#1 -38956598#1"/>
<taz id="43" edges="-329989226#0 -329989226#1 -329989226#2 329989226#0 329989226#1 329989226#2 19893612#1 19893612#2 19893612#3 19893612#4 19893612#5 19893612#6 19893612#7 19893612#8 132216829#1 132216829#2 132216829#3 396642609#0 464897412#1 454238789"/>
<taz id="13" edges="465416573 465416574 465416578#0 129811153#0 129811153#1 -129811153#0 -129811153#1 461254934 -461254934 399697652 -399697652 37723610#1 -37723610#1 165257881#0 -165257881#0 455083999 -455083999 461254935 -461254935"/>
<taz id="38" edges="35565810 48921993 109752886 -109752886 199560670 453989324"/>
<taz id="11" edges="455083975#0 465649964#0 465649965#0 21338774 -21338774 165257880#0 165257880#1 165257880#2 36672938#1 36672938#2 -36672938#1 -36672938#2 219132793 19892255#0 19892255#1 19892255#2 19892255#4 19892255#5"/>
<taz id="10" edges="19895957 19895958 19914255 48678926 474555858 377233441#0 377233442 43710578 165325232 -165325232 43710577 -43710577 474555863#0 -474555863#0 474555867#0 474555867#2 -474555867#0 -474555867#2 456353760#0 -456353760#0 377233443 -377233443 464718641 -464718641 48678925"/>
<taz id="39" edges="453989310 274693150#0 274693150#1 274693150#2 332695584#0 332695584#1 332695584#2 332695584#3 332695584#4 453989314 453989315 45560932#0 165334551 -165334551 165334552 -165334552 165334553 -165334553 48921991#0 48921991#1 393659757#3 465586406 -465586406 329384208 -329384208"/>
<taz id="12" edges="165265049#0 165265049#1 165265049#2 -455083972#0 -455083982#0 21333766#1 455084000#0 455084001#1 465653989 36606094#0 36606094#1 -36606094#0 -36606094#1 35928368 114876252 36672937#0 308658929#0 465653666 -465653666 465653669 -465653669"/>
<taz id="15" edges="60116378#0 -456316924 -456316923 -456316925 36606092#0 -36606092#0 36606095 -36606095 422636127#0 422636127#1 465653668 -465653668 104476237"/>
<taz id="14" edges="19895498 352905244 -385754231 385754231 428978766#2 456316924 456316925 -43710578 24263070 19896203#0 19896203#1 60116375 19900948 -19900948 19900946#0 19900946#1 352392847#0 352392847#1 -385754230 352392845 -352392845 376479646#0 376479646#1 376479646#2 376479646#3 376479646#4 376479646#5 376479646#7 376479646#8 376479646#9 467514126 39442471 -39442471 19900947#0 19900947#1 60116377#0 60116377#1 60116379 -60116379 356391598 -356391598 19914256 104476236#0 104476236#1 19895495"/>
<taz id="17" edges="-385879098#0 -479572754#1 -479572754#0"/>
<taz id="16" edges="455083972#0 455083982#0 165325607 -165325607 465418193 -465418193"/>
<taz id="19" edges="455083965 -453963142 -453981161#0 300627772#1 479572754#0 479572754#1 24221231#1 466675150"/>
<taz id="32" edges="104476234#1 19894605#0 19894605#1 19894605#2 312955854#0 312955854#1 312955854#2 312955854#3 312955854#4 312955854#5 274693149 330718542 164974773#0 48808784 274693142#0 274693142#2 274693142#3 39368249#0 86980320 -86980320"/>
<taz id="31" edges="456314146 456314147#0"/>
<taz id="30" edges="465414045 -465414045 465414050 -465414050 329384210 -329384210 19891259 13501273 465413249 -465413249 465585477#1 -465585477#1"/>
<taz id="37" edges="331089331#0 -454238785 -454215275 -454215277#0"/>
<taz id="36" edges="34286991 34287015 34287039 34287041 356979511 4320462#0 4320462#1 20318110 101976281 -101976281 331089331#1 352905364#0 352905364#1 352905364#3 352905364#4 450724839#1 274693149 19908070#0 19908070#1 165325229 454842388 320900388#0 320900388#1 34287027 458303421"/>
<taz id="35" edges="4687530#0 464936533 464943212#0 45560666"/>
<taz id="34" edges="48921999 -48921999 107613002#0 107613002#1 107613002#2 107613002#3 107613002#4 36519031 4686990#0 329384209#0 329384209#1 356391517#0 455083992 48921992 274693147 415626770#1 415626772#1 415626772#0 356391516 4320454#0 4320454#1 4320454#2 329384213#0 329384213#2 329384213#3 329384213#4 453989325 34144392#0 453989323#0 329384205 453989322"/>
<taz id="33" edges="-464936533 -464943212#0 164974773#0 48808784 39368249#0"/>
<taz id="18" edges="19898458 19895490#0 19895490#1 19895490#2 422636128#1 422636128#2 19895959#0 19895959#1 19895959#2 19895959#3 19895959#5 219132792 -219132792 455083996 -455083996 219132794#0 219132794#1 219132794#2"/>
</tazs>
